analyticsdf/__init__.py
analyticsdf/analyticsdataframe.py
analyticsdf-0.0.7.dist-info/LICENSE
analyticsdf-0.0.7.dist-info/METADATA
analyticsdf-0.0.7.dist-info/WHEEL
analyticsdf-0.0.7.dist-info/top_level.txt
analyticsdf-0.0.7.dist-info/RECORD
